canon_keeper/__init__.py
canon_keeper/__main__.py
canon_keeper/install.py
canon_keeper-0.3.0.dist-info/METADATA
canon_keeper-0.3.0.dist-info/WHEEL
canon_keeper-0.3.0.dist-info/entry_points.txt
canon_keeper-0.3.0.dist-info/RECORD
