Metadata-Version: 2.4
Name: canon-keeper
Version: 0.3.0
Summary: Copilot memory persistence - just an installer, no dependencies
Project-URL: Homepage, https://github.com/phantom-man/canon_keeper
Project-URL: Repository, https://github.com/phantom-man/canon_keeper
Project-URL: Documentation, https://github.com/phantom-man/canon_keeper/blob/main/README.md
Author-email: Phantom-man <damienfosborn@gmail.com>
License: MIT
Keywords: ai,copilot,github,instructions,memory,session
Classifier: Development Status :: 4 - Beta
Classifier: Intended Audience :: Developers
Classifier: License :: OSI Approved :: MIT License
Classifier: Programming Language :: Python :: 3
Classifier: Programming Language :: Python :: 3.8
Classifier: Programming Language :: Python :: 3.9
Classifier: Programming Language :: Python :: 3.10
Classifier: Programming Language :: Python :: 3.11
Classifier: Programming Language :: Python :: 3.12
Classifier: Topic :: Software Development :: Libraries :: Python Modules
Requires-Python: >=3.8
